gustavo_image_processor/__init__.py
gustavo_image_processor/processing/__init__.py
gustavo_image_processor/processing/combination.py
gustavo_image_processor/processing/transformation.py
gustavo_image_processor/utils/__init__.py
gustavo_image_processor/utils/io.py
gustavo_image_processor/utils/plot.py
gustavo_image_processor-0.0.2.dist-info/METADATA
gustavo_image_processor-0.0.2.dist-info/WHEEL
gustavo_image_processor-0.0.2.dist-info/top_level.txt
gustavo_image_processor-0.0.2.dist-info/RECORD
